sparsesampler/__init__.py
sparsesampler/preprocessing.py
sparsesampler/sampling.py
sparsesampler/utils.py
sparsesampler/visualization.py
sparsesampler-1.0.0.dist-info/licenses/LICENSE
sparsesampler-1.0.0.dist-info/METADATA
sparsesampler-1.0.0.dist-info/WHEEL
sparsesampler-1.0.0.dist-info/top_level.txt
sparsesampler-1.0.0.dist-info/RECORD
